contact_form/__init__.py
contact_form/forms.py
contact_form/models.py
contact_form/tests.py
contact_form/urls.py
contact_form/views.py
contact_form/locale/es_ES/LC_MESSAGES/django.mo
contact_form/locale/es_ES/LC_MESSAGES/django.po
contact_form/locale/pt_BR/LC_MESSAGES/django.mo
contact_form/locale/pt_BR/LC_MESSAGES/django.po
contact_form/locale/ru/LC_MESSAGES/django.mo
contact_form/locale/ru/LC_MESSAGES/django.po
contact_form/templates/contact_form/contact.html
contact_form/templates/contact_form/contact_completed.html
contact_form/templates/contact_form/email_subject.txt
contact_form/templates/contact_form/email_template.txt
django_contact_form_gv-0.9.1.dist-info/licenses/LICENSE
django_contact_form_gv-0.9.1.dist-info/METADATA
django_contact_form_gv-0.9.1.dist-info/WHEEL
django_contact_form_gv-0.9.1.dist-info/top_level.txt
django_contact_form_gv-0.9.1.dist-info/RECORD
